saml_reader/__init__.py
saml_reader/cert.py
saml_reader/cli.py
saml_reader/har.py
saml_reader/text_reader.py
saml_reader/saml/__init__.py
saml_reader/saml/base.py
saml_reader/saml/errors.py
saml_reader/saml/oli.py
saml_reader/saml/parser.py
saml_reader/validation/__init__.py
saml_reader/validation/graph_suite.py
saml_reader/validation/input_validation.py
saml_reader/validation/mongo.py
saml_reader/web/__init__.py
saml_reader/web/app.py
saml_reader/web/cli_hook.py
saml_reader/web/run.py
saml_reader/web/callbacks/__init__.py
saml_reader/web/callbacks/analyze.py
saml_reader/web/callbacks/home.py
saml_reader/web/callbacks/index.py
saml_reader/web/layouts/__init__.py
saml_reader/web/layouts/analyze.py
saml_reader/web/layouts/home.py
saml_reader/web/layouts/index.py
saml_reader-0.0.7.dist-info/LICENSE
saml_reader-0.0.7.dist-info/METADATA
saml_reader-0.0.7.dist-info/WHEEL
saml_reader-0.0.7.dist-info/entry_points.txt
saml_reader-0.0.7.dist-info/top_level.txt
saml_reader-0.0.7.dist-info/RECORD
