Metadata-Version: 2.1
Name: saml_reader
Version: 0.0.7
Summary: SAML response parser for MongoDB Cloud
Home-page: https://github.com/clegaspi/saml_reader
Author: Christian Legaspi
Author-email: christian.legaspi@mongodb.com
License-File: LICENSE
Requires-Dist: pyperclip
Requires-Dist: haralyzer
Requires-Dist: python3-saml
Requires-Dist: cryptography
Requires-Dist: networkx
Requires-Dist: xmlsec >=1.3.14
Requires-Dist: dash
Requires-Dist: dash-extensions
